[
  {
	"id": 0,
    "Min H/C": "",
    "Mand. Time": "",
    "Offense Reference": "c. 265 s. 13A(a)",
    "Notes": "",
    "Offense Penalty Reference": "",
    "Max H/C": "2 1/2 years",
    "Grid": "Yes",
    "Staircase Factor": "",
    "Offense": "A&B c. 265 s. 13A(a)",
    "Penalty Type ": "Misd.",
    "Min Prison": "",
    "Max Prison": "",
    "Offense Seriousness Level": 3.0
  },
  {
	"id": 1,
    "Min H/C": "",
    "Mand. Time": "",
    "Offense Reference": "c. 265 s. 13K(a 1/2)",
    "Notes": "Note K",
    "Offense Penalty Reference": "",
    "Max H/C": "2 1/2 years",
    "Grid": "Yes",
    "Staircase Factor": "",
    "Offense": "A&B ON 60+/DISABLED c. 265 s. 13K(a 1/2)",
    "Penalty Type ": "Felony",
    "Min Prison": "",
    "Max Prison": "3 years",
    "Offense Seriousness Level": "(4)"
  },
  {
	"id": 2,
    "Min H/C": "",
    "Mand. Time": "",
    "Offense Reference": "c. 265 s. 13J",
    "Notes": "Note A",
    "Offense Penalty Reference": "",
    "Max H/C": "2 1/2 years",
    "Grid": "Yes",
    "Staircase Factor": "",
    "Offense": "A&B ON CHILD WITH INJURY c. 265 s. 13J",
    "Penalty Type ": "Felony",
    "Min Prison": "",
    "Max Prison": "5 years",
    "Offense Seriousness Level": 5.0
  },
  {
	"id": 3,
    "Min H/C": "",
    "Mand. Time": "",
    "Offense Reference": "c. 265 s. 13J",
    "Notes": "Note A",
    "Offense Penalty Reference": "",
    "Max H/C": "2 1/2 years",
    "Grid": "Yes",
    "Staircase Factor": "",
    "Offense": "A&B ON CHILD WITH SUBSTANTIAL INJURY c. 265 s. 13J",
    "Penalty Type ": "Felony",
    "Min Prison": "",
    "Max Prison": "15 years",
    "Offense Seriousness Level": 7.0
  },
  {
	"id": 0,
    "Min H/C": "",
    "Mand. Time": "",
    "Offense Reference": "c. 127 s. 38B(b)",
    "Notes": "Note K",
    "Offense Penalty Reference": "",
    "Max H/C": "2 1/2 years",
    "Grid": "Yes",
    "Staircase Factor": "",
    "Offense": "A&B ON CORRECTIONAL FACILITY EMPLOYEE c. 127 s. 38B(b)",
    "Penalty Type ": "Felony",
    "Min Prison": "",
    "Max Prison": "10 years",
    "Offense Seriousness Level": "(4)"
  },
  {
	"id": 4,
    "Min H/C": "",
    "Mand. Time": "",
    "Offense Reference": "c. 265 s. 13K(b)",
    "Notes": "",
    "Offense Penalty Reference": "",
    "Max H/C": "2 1/2 years",
    "Grid": "Yes",
    "Staircase Factor": "",
    "Offense": "A&B ON ELDER (60+)/DISABLED PERSON; BODILY INJURY c. 265 s. 13K(b)",
    "Penalty Type ": "Felony",
    "Min Prison": "",
    "Max Prison": "5 years",
    "Offense Seriousness Level": 4.0
  },
  {
	"id": 5,
    "Min H/C": "",
    "Mand. Time": "",
    "Offense Reference": "c. 265 s. 13K(c)",
    "Notes": "",
    "Offense Penalty Reference": "",
    "Max H/C": "2 1/2 years",
    "Grid": "Yes",
    "Staircase Factor": "",
    "Offense": "A&B ON ELDER (60+)/DISABLED PERSON; SERIOUS BODILY INJURY c. 265 s. 13K(c)",
    "Penalty Type ": "Felony",
    "Min Prison": "",
    "Max Prison": "10 years",
    "Offense Seriousness Level": 6.0
  },
  {
	"id": 6,
    "Min H/C": "",
    "Mand. Time": "",
    "Offense Reference": "c. 265 s. 13F",
    "Notes": "",
    "Offense Penalty Reference": "",
    "Max H/C": "2 1/2 years",
    "Grid": "Yes",
    "Staircase Factor": "",
    "Offense": "A&B ON PERSON WITH INTELLECTUAL DISABILITY c. 265 s. 13F",
    "Penalty Type ": "Felony",
    "Min Prison": "",
    "Max Prison": "5 years",
    "Offense Seriousness Level": 4.0
  },
  {
	"id": 7,
    "Min H/C": "",
    "Mand. Time": "",
    "Offense Reference": "c. 265 s. 13F",
    "Notes": "",
    "Offense Penalty Reference": "",
    "Max H/C": "",
    "Grid": "Yes",
    "Staircase Factor": "",
    "Offense": "A&B ON PERSON WITH INTELLECTUAL DISABILITY, SUBSQ. OFF c. 265 s. 13F",
    "Penalty Type ": "Felony",
    "Min Prison": "",
    "Max Prison": "10 years",
    "Offense Seriousness Level": 5.0
  },
  {
	"id": 8,
    "Min H/C": "90 days",
    "Mand. Time": "",
    "Offense Reference": "c. 265 s. 13D",
    "Notes": "",
    "Offense Penalty Reference": "",
    "Max H/C": "2 1/2 years",
    "Grid": "Yes",
    "Staircase Factor": "",
    "Offense": "A&B ON PUBLIC EMPLOYEE c. 265 s. 13D",
    "Penalty Type ": "Misd.",
    "Min Prison": "",
    "Max Prison": "",
    "Offense Seriousness Level": 3.0
  },
  {
	"id": 9,
    "Min H/C": "",
    "Mand. Time": "",
    "Offense Reference": "c. 265 s. 39(a)",
    "Notes": "",
    "Offense Penalty Reference": "",
    "Max H/C": "2 1/2 years",
    "Grid": "Yes",
    "Staircase Factor": "",
    "Offense": "A&B OR PROPERTY DAMAGE TO INTIMIDATE FOR RACE/RELIGION c. 265 s. 39(a)",
    "Penalty Type ": "Misd.",
    "Min Prison": "",
    "Max Prison": "",
    "Offense Seriousness Level": 3.0
  },
  {
	"id": 10,
    "Min H/C": "",
    "Mand. Time": "",
    "Offense Reference": "c. 265 s. 39(b)",
    "Notes": "",
    "Offense Penalty Reference": "",
    "Max H/C": "",
    "Grid": "Yes",
    "Staircase Factor": "",
    "Offense": "A&B OR PROPERTY DAMAGE TO INTIMIDATE FOR RACE/RELIGION, BODILY INJURY  c. 265 s. 39(b)",
    "Penalty Type ": "Felony",
    "Min Prison": "",
    "Max Prison": "5 years",
    "Offense Seriousness Level": 4.0
  },
  {
	"id": 11,
    "Min H/C": "",
    "Mand. Time": "",
    "Offense Reference": "c. 265 s. 39(b)",
    "Notes": "",
    "Offense Penalty Reference": "",
    "Max H/C": "2 1/2 years",
    "Grid": "Yes",
    "Staircase Factor": "",
    "Offense": "A&B OR PROPERTY DAMAGE TO INTIMIDATE FOR RACE/RELIGION, BODILY INJURY, ARMED  c. 265 s. 39(b)",
    "Penalty Type ": "Felony",
    "Min Prison": "",
    "Max Prison": "10 years",
    "Offense Seriousness Level": 6.0
  },
  {
	"id": 12,
    "Min H/C": "",
    "Mand. Time": "",
    "Offense Reference": "c. 265 s. 13C",
    "Notes": "",
    "Offense Penalty Reference": "",
    "Max H/C": "2 1/2 years",
    "Grid": "Yes",
    "Staircase Factor": "",
    "Offense": "A&B TO COLLECT LOAN c. 265 s. 13C",
    "Penalty Type ": "Felony",
    "Min Prison": "3 years",
    "Max Prison": "5 years",
    "Offense Seriousness Level": 4.0
  },
  {
	"id": 13,
    "Min H/C": "",
    "Mand. Time": "",
    "Offense Reference": "c. 265 s. 13C",
    "Notes": "Note B",
    "Offense Penalty Reference": "",
    "Max H/C": "",
    "Grid": "Yes",
    "Staircase Factor": "",
    "Offense": "A&B TO COLLECT LOAN, SUBSQ. OFF. c. 265 s. 13C",
    "Penalty Type ": "Felony",
    "Min Prison": "5 years",
    "Max Prison": "10 years",
    "Offense Seriousness Level": 5.0
  },
  {
	"id": 14,
    "Min H/C": "",
    "Mand. Time": "",
    "Offense Reference": "c. 127 s. 38B(c)",
    "Notes": "Note K",
    "Offense Penalty Reference": "",
    "Max H/C": "2 1/2 years",
    "Grid": "Yes",
    "Staircase Factor": "",
    "Offense": "A&B WITH BODILY SUBSTANCE ON CORRECTIONAL FACILITY EMPLOYEE c. 127 s. 38B(c)",
    "Penalty Type ": "Felony",
    "Min Prison": "",
    "Max Prison": "10 years",
    "Offense Seriousness Level": "(4)"
  },
  {
	"id": 15,
    "Min H/C": "",
    "Mand. Time": "",
    "Offense Reference": "c. 265 s. 15A(a)",
    "Notes": "Note G",
    "Offense Penalty Reference": "",
    "Max H/C": "2 1/2 years",
    "Grid": "Yes",
    "Staircase Factor": "No/Minor Injury",
    "Offense": "A&B WITH DANGEROUS WEAPON +60 c. 265 s. 15A(a)",
    "Penalty Type ": "Felony",
    "Min Prison": "",
    "Max Prison": "10 years",
    "Offense Seriousness Level": 3.0
  },
  {
	"id": 16,
    "Min H/C": "",
    "Mand. Time": "",
    "Offense Reference": "c. 265 s. 15A(a)",
    "Notes": "Note G",
    "Offense Penalty Reference": "",
    "Max H/C": "2 1/2 years",
    "Grid": "Yes",
    "Staircase Factor": "Moderate Injury",
    "Offense": "A&B WITH DANGEROUS WEAPON +60 c. 265 s. 15A(a) ",
    "Penalty Type ": "Felony",
    "Min Prison": "",
    "Max Prison": "10 years",
    "Offense Seriousness Level": 4.0
  },
  {
	"id": 17,
    "Min H/C": "",
    "Mand. Time": "",
    "Offense Reference": "c. 265 s. 15A(a)",
    "Notes": "Note A / Note G",
    "Offense Penalty Reference": "",
    "Max H/C": "2 1/2 years",
    "Grid": "Yes",
    "Staircase Factor": "Significant Injury",
    "Offense": "A&B WITH DANGEROUS WEAPON +60 c. 265 s. 15A(a) ",
    "Penalty Type ": "Felony",
    "Min Prison": "",
    "Max Prison": "10 years",
    "Offense Seriousness Level": 6.0
  },
  {
	"id": 0,
    "Min H/C": "2 years",
    "Mand. Time": "",
    "Offense Reference": "c. 265 s. 15A(a)",
    "Notes": "Note G",
    "Offense Penalty Reference": "",
    "Max H/C": "2 1/2 years",
    "Grid": "Yes",
    "Staircase Factor": "No / Minor Injury",
    "Offense": "A&B WITH DANGEROUS WEAPON +60, SUBSQ.OFF c. 265 s. 15A(a)",
    "Penalty Type ": "Felony",
    "Min Prison": "2 years",
    "Max Prison": "10 years",
    "Offense Seriousness Level": 4.0
  }
]